[{"family":"MaterialIcons","fonts":[{"asset":"fonts/MaterialIcons-Regular.otf"}]},{"family":"Aller","fonts":[{"weight":700,"style":"italic","asset":"assets/fonts/aller/Aller_Std_Bd.ttf"},{"style":"italic","asset":"assets/fonts/aller/Aller_Std_It.ttf"},{"weight":400,"style":"normal","asset":"assets/fonts/aller/Aller_Std_Rg.ttf"},{"weight":100,"style":"normal","asset":"assets/fonts/aller/Aller_Std_Lt.ttf"},{"style":"normal","asset":"assets/fonts/aller/AllerDisplay_Std_Rg.ttf"}]},{"family":"packages/cupertino_icons/CupertinoIcons","fonts":[{"asset":"packages/cupertino_icons/assets/CupertinoIcons.ttf"}]},{"family":"packages/line_awesome_flutter/LineAwesomeIcons","fonts":[{"weight":400,"asset":"packages/line_awesome_flutter/lib/fonts/LineAwesome.ttf"}]}]